MANIFEST.in
README.txt
setup.cfg
setup.py
Products/__init__.py
Products.PyConBrasil.egg-info/PKG-INFO
Products.PyConBrasil.egg-info/SOURCES.txt
Products.PyConBrasil.egg-info/dependency_links.txt
Products.PyConBrasil.egg-info/entry_points.txt
Products.PyConBrasil.egg-info/namespace_packages.txt
Products.PyConBrasil.egg-info/not-zip-safe
Products.PyConBrasil.egg-info/requires.txt
Products.PyConBrasil.egg-info/top_level.txt
Products/PyConBrasil/Imprensa.py
Products/PyConBrasil/Inscricao.py
Products/PyConBrasil/InscricaoCorporativa.py
Products/PyConBrasil/Inscricoes.py
Products/PyConBrasil/Palestra.py
Products/PyConBrasil/PalestraRelampago.py
Products/PyConBrasil/README.txt
Products/PyConBrasil/Trabalho.py
Products/PyConBrasil/Treinamento.py
Products/PyConBrasil/UIDRenamer.py
Products/PyConBrasil/__init__.py
Products/PyConBrasil/ck_nr.pt
Products/PyConBrasil/config.py
Products/PyConBrasil/configure.zcml
Products/PyConBrasil/interfaces.py
Products/PyConBrasil/numberator.py
Products/PyConBrasil/setuphandlers.py
Products/PyConBrasil/utils.py
Products/PyConBrasil/version.txt
Products/PyConBrasil/Extensions/certificate.py
Products/PyConBrasil/Extensions/workflow_scripts.py
Products/PyConBrasil/browser/__init__.py
Products/PyConBrasil/browser/configure.zcml
Products/PyConBrasil/browser/helper.py
Products/PyConBrasil/browser/interfaces.py
Products/PyConBrasil/docs/__init__.py
Products/PyConBrasil/docs/inscricao.txt
Products/PyConBrasil/docs/inscricaocorporativa.txt
Products/PyConBrasil/locales/Products.PyConBrasil.pot
Products/PyConBrasil/locales/manual.pot
Products/PyConBrasil/locales/rebuildAll.sh
Products/PyConBrasil/locales/pt_BR/LC_MESSAGES/Products.PyConBrasil.po
Products/PyConBrasil/model/PyConBrasil.png
Products/PyConBrasil/model/PyConBrasil.zuml
Products/PyConBrasil/model/clean_trash.sh
Products/PyConBrasil/model/generate.conf
Products/PyConBrasil/model/generate_source.sh
Products/PyConBrasil/model/inscricao_workflow.png
Products/PyConBrasil/model/inscricoes_workflow.png
Products/PyConBrasil/model/palestra_workflow.png
Products/PyConBrasil/profiles/default/catalog.xml
Products/PyConBrasil/profiles/default/factorytool.xml
Products/PyConBrasil/profiles/default/import_steps.xml
Products/PyConBrasil/profiles/default/metadata.xml
Products/PyConBrasil/profiles/default/propertiestool.xml
