Metadata-Version: 1.0
Name: Products.PyConBrasil
Version: 2.4.1
Summary: Package for managing papers and the registration process for PyConBrasil.
Home-page: http://svn.plone.org/svn/collective/Products.PyConBrasil/
Author: APyB - Associacao Python Brasil
Author-email: contato@python.org.br
License: GPL
Keywords: pyconbrasil plone zope registration
Platform: UNKNOWN
Classifier: Programming Language :: Python
Classifier: Framework :: Plone
Classifier: Framework :: Zope2
